{
  "ALARMS": {
    "ALARMS": "Alarma(s)",
    "DO_NOT_DISTURB_ALARM": "No molestar",
    "DOOR_ALARM": "Alarma de puerta",
    "SOS_ALARM": "Alarma SOS",
    "WINDOW_ALARM": "Alarma de ventana"
  },
  "AREAS": {
    "ADD_SUBGROUP": "Añadir subgrupo",
    "AREAS": "Áreas",
    "CLEAR_SELECTION": "Borrar selección",
    "CREATE_NEW_GROUP": "Crear nuevo grupo",
    "DELETE_GROUP": "Borrar grupo",
    "DELETE_SELECTED": "Eliminar selección",
    "DESCRIPTION": "Descripción",
    "DRAG_AND_DROP_A_ROOM_OR_AREA_FROM_THE_LEFT_COLUMN_TO_THIS_COLUMN_AND_CREATE_A_NEW_ORGANIZATION": "Arrastrar una habitación o área desde la columna izquierda a esta columna y crear una nueva organización",
    "DRAG_AND_DROP_INTO_THE_RIGHT_COLUMN_OR_SELECT_AND_ADD_TO_THE_LIST_TO_CREATE_A_NEW_ORGANIZATION": "Arrastrar a la columna derecha o seleccionar y añadir a la lista para crear una nueva organización",
    "EDIT_SEASON_PRESETS": "Editar selección de estación",
    "HOTEL_ACCESS": "Acceso a hotel",
    "MAKE_DEFAULT": "Hacer por defecto",
    "NO_SEASON_PRESET": "No hay una selección de estación asignada.",
    "SEASON_PRESETS": "Selección de estaciones",
    "UNIQUE_BLE_NUMBER": "Número BLE ya en uso",
    "UNMAKE_DEFAULT": "Deshacer por defecto"
  },
  "BEACONS": {
    "ADD_BLACKLIST": "Añadir lista negra",
    "AVAILABLE_GROUPS": "Grupos disponibles",
    "CONFIRM_REVOKE": "¿Está seguro que quiere eliminar los accesos para este usuario?",
    "MAC": "Mac",
    "NO_CARD": "Presente tarjeta en el lector",
    "REVOKE_PERMISSIONS": "Eliminar accesos",
    "STAFF_DETAILS": "Detalles de staff",
    "USER_TYPE": "Tipo de usuario",
    "WRITE_STAFF_BEACON": "Crear llaves de staff"
  },
  "BLACKLIST": {
    "BEACON_IS_REQUIRED": "Llave requerida",
    "BLACKLIST_BEACON_IS_REQUIRED": "Lista negra de llaves requerida",
    "BLACKLIST_DATE_IS_REQUIRED": "Fecha de lista negra requerida",
    "BLACKLIST_GROUP_IS_REQUIRED": "Grupo de lista negra requerida",
    "BLACKLIST_SPACE_IS_REQUIRED": "Espacio de lista negra requerido",
    "CHANGE_TO_GROUP": "Cambiar a grupo",
    "GROUP": "Grupo",
    "GROUP_IS_REQUIRED": "Se necesita grupo",
    "SPACE_IS_REQUIRED": "Se necesita espacio"
  },
  "BOOKINGS": {
    "ACTIONS": "Acciones",
    "ADD_NEW": "Añadir nuevo",
    "ADDITIONAL_AREAS": "Áreas adicionales",
    "AREA_REQUIRED": "Debe seleccionar un área válida",
    "BACK_TO_BOOKING_DETAILS": "Volver a detalles de reserva",
    "BOOKING": "Reserva",
    "BOOKING_DATES": "Fechas de reserva",
    "BOOKING_DETAILS": "Detalles de reserva",
    "CHECK-IN": "Check-in",
    "CHECK-IN FOR": "Check-in para {{guestName}}",
    "CHECK-IN_COMPLETED": "Check-in completado",
    "CHECK-IN_DATE": "Fechas de Check-in",
    "CHECK-IN_DETAILS": "Detalles de Check-in",
    "CHECK-IN_TIME": "Hora de Check-in",
    "CHECK-IN_TIME_CANNOT_BE_AFTER_CHECKOUT_TIME": "La hora de Check-in no puede ser posterior a la de Check-out",
    "CHECK-OUT_COMPLETED": "Check-out completado",
    "CHECK-OUT_DATE": "Fecha de Check-out",
    "CHECK-OUT_DATE_MUST_BE_LATER_THAN_CHECK-IN_DATE": "La fecha de Check-out debe ser posterior a la de Check-in",
    "CHECK-OUT_PENDING": "Check-out pendiente",
    "CHECK-OUT_TIME": "Hora de Check-out",
    "CHECK-OUT_WARNING": "Las llaves de huésped deben ser reasignadas",
    "COMFORT_CONFIGURATION": "Configuración de Comfort",
    "DATE_REQUIRED": "Fecha requerida",
    "DELETE": "Borrar",
    "DUPLICATE": "Duplicar",
    "EDIT": "Editar",
    "GROUPS": "Grupos",
    "GUEST_DETAILS": "Detalles del huésped",
    "GUEST_NAME": "Nombre del huésped",
    "GUEST_NAME_CANNOT_EXCEED_70_CHARACTERS": "El nombre del huésped no debe exceder de 70 caracteres",
    "GUEST_NAME_IS_REQUIRED": "Se requiere nombre de huésped",
    "GUEST_NAME_MUST_BE_AT_LEAST_TWO_CHARACTERS": "El nombre del huésped debe tener al menos 2 caracteres",
    "GUEST_PHONE_NUMBER": "Número de teléfono de huésped",
    "GUEST_PHONE_NUMBER_IS_REQUIRED": "Se requiere número de teléfono del huésped",
    "GUEST_PHONE_NUMBER_PATTERN": "El número de teléfono debe tener +[Código internacional] y 9 números al menos",
    "GUEST_SURNAME": "Apellido del huésped",
    "GUEST_SURNAME_CANNOT_EXCEED_70_CHARACTERS": "El nombre del huésped no debe exceder de 70 caracteres",
    "GUEST_SURNAME_IS_REQUIRED": "Se requiere nombre de huésped",
    "GUEST_SURNAME_MUST_BE_AT_LEAST_TWO_CHARACTERS": "El nombre del huésped debe tener al menos 2 caracteres",
    "MODIFY_CHECK-IN": "Modificar parámetros de Check-in",
    "NO_ROOM_SPECIFIED_MESSAGE": "La reserva no puede completarse hasta que se especifique una habitación o suite. Mientras tanto puede hacerse un pre check-in",
    "NUMBER_OF_NIGHTS": "Número de noches",
    "PRE_CHECK-IN": "Pre check-in",
    "ROOM_N": "Habitación nº",
    "ROOM_VALIDATION": "Pore favor seleccione una habitación",
    "SAVE AND DUPLICATE": "Guardar y duplilcar",
    "SAVE_AND_NEW": "Guardar y crear nueva",
    "SHOW_CHECK-OUTS": "Mostrar check-outs",
    "SHOW_NON_AVAILABLE_ROOMS": "Mostrar habitaciones no disponibles",
    "SUITE": "Suite",
    "VALIDATION": "Validación",
    "WRITE_BEACON": "Escribir llave"
  },
  "CAROUSEL": {
    "NO_ITEMS": "Todas las áreas se han añadido",
    "SELECT_TITLE": "Por favor seleccionar una o más áreas a las que va a tener acceso el usuario",
    "YOU_HAVE_NOT_ADDED_ANY_ITEM_YET": "No se ha añadido ningún elemento todavía",
    "MAX_ITEMS_ERROR": "Sólo puede seleccionar {{maxItems}} grupos.",
    "MAX_BLE_GROUPS_ERROR": "Sólo puede seleccionar {{maxItems}} grupos.",
    "MAX_CISA_CATEGORIES_ERROR": "Sólo puede seleccionar {{maxItems}} categorías.",
    "MAX_CISA_ZONES_ERROR": "Sólo puede seleccionar {{maxItems}} zonas."
  },
  "CHECK_BEACONS": {
    "BEACON_INTERVAL": "Intervalo de llaves",
    "HIDE_DETAILS": "Ocultar detalles",
    "KEY_ACTION_FRAME_NUMBER": "Key action frame number",
    "KEY_PRESENCE_FRAME_NUMBER": "Key  presence frame number",
    "KEY_PRESENCE_INTERVAL": "Key presence interval",
    "LABEL": "Etiqueta",
    "MAC": "Mac",
    "PASSPARTOUT": "Passepartout",
    "ROOM": "Habitación",
    "SHOW_DETAILS": "Mostrar detalles",
    "SPACE_GROUPS": "Grupos",
    "SUMMARY": "Resumen",
    "TITLE": "Check key devices",
    "TX_POWER": "Tx power",
    "USER": "Usuario"
  },
  "COMFORT_PRESET": {
    "ADD_NEW": "Añadir nuevo",
    "COMFORT_PRESETS": "Parámetros de confort",
    "PLACEHOLDERS": {
      "DELTA_ECONOMY": "Delta economía",
      "DELTA_PRE_COMFORT": "Delta pre confort",
      "FAN_SPEED": "Velocidad de ventilador",
      "SEASON": "Estación",
      "TEMPERATURE": "Temperatura"
    },
    "VALIDATIONS": {
      "NAME_MAX_SIZE": "El nombre de la selección de confort no debe exceder de 70 caracteres",
      "NAME_MIN_SIZE": "El nombre de la selección de confort debe tener al menos 2 caracteres",
      "NAME_REQUIRED": "Es necesario  un nombre para la selección de confort",
      "TEMPERATURE_PATTERN": "La temperatura debes er un número",
      "TEMPERATURE_REQUIRED": "Se  necesita un valor de temperatura"
    }
  },
  "COMMISIONING": {
    "COMMISIONING_PARAMETERS": "Parámetros de puesta en marcha",
    "KEY_BEACON": "Key key device",
    "ROOM_BEACON": "Llave de habitación"
  },
  "COMMON": {
    "#COM": "#COM",
    "ACTIONS": "Acciones",
    "ACTIVE": "Activo",
    "ADD": "Añadir",
    "ADD_NEW": "Añadir nuevo",
    "ALARMS": "Alarmas",
    "ALL": "Todo",
    "AN_UNEXPECTED_ERROR_HAS_OCCURRED": "Se ha producido un error no esperado",
    "ARE_YOU_SURE_YOU_WANT_TO_DELETE_THE_ITEM": "¿Está seguro que quiere borrar el elemento?",
    "AUTO": "Auto",
    "BACK": "Volver",
    "BEACON": "Key device",
    "BEACONS": "key devices",
    "BLACKLIST": "lista negra",
    "BLACKLIST_TITLE": "Lista negra",
    "BOOKINGS": "Reservas",
    "CANCEL": "Cancelar",
    "CARD_INFO": "Información de tarjeta",
    "CHOOSE": "Elegir",
    "CLOSE": "Cerrar",
    "CONFIRM": "Confirmar",
    "COOLING": "Frío",
    "DATE": "Fecha",
    "DAY": "Día",
    "DELETE": "Borrar",
    "DESCRIPTION": "Descripción",
    "DONE": "Hecho",
    "DOWNLOAD": "Descargar",
    "EDIT": "Editar",
    "EDIT_GROUP": "Editar grupo",
    "EVENTS": "eventos",
    "FROM": "Desde",
    "GROUP": "Grupo",
    "GROUPS": "Grupos",
    "GUEST": "Huésped",
    "HEATING": "Calor",
    "INACTIVE": "Inactivo",
    "LAST_NAME": "Apellido",
    "MANUAL": "Manual",
    "MARK_DEFAULT": "Poner por defecto",
    "MONTH": "Mes",
    "NAME": "Nombre",
    "NEITHER": "Ninguno",
    "NEXT": "Siguiente",
    "NO": "No",
    "OFF": "Off",
    "OPERATION_COMPLETED_SUCCESSFULLY": "Operación completada con éxito",
    "PARAMETER": "Parámetro",
    "REPORTS": "Informes",
    "ROLE": "Rol",
    "ROOM": "Habitación",
    "ROOMS": "Habitaciones",
    "ROOM_AND_ACCESS_INFORMATION": "Habitación e información de acceso",
    "SAVE": "Salvar",
    "SPACE": "Espacio",
    "SPACES": "Espacios",
    "SPEED_1": "Baja",
    "SPEED_2": "Media",
    "SPEED_3": "Alta",
    "STAFF": "Staff",
    "STATUS": "Estado",
    "SUCCESS": "Éxito",
    "SUITES": "Suites",
    "SURNAME": "Apellido",
    "TASK_TYPES": "Tipos de tarea",
    "TO": "A",
    "TYPE": "Tipo",
    "UPLOAD": "Cargar",
    "USERNAME": "Nombre de usuario",
    "VALUE": "Valor",
    "WARNING": "Warning",
    "WRITE_WITH_QR_CODE": "Escribir código QR",
    "YES": "Sí"
  },
  "COMMON_VALIDATION": {
    "GROUP_NAME_CANNOT_EXCEED_70_CHARACTERS": "El nombre del grupo no debe exceder de 70 caracteres",
    "GROUP_NAME_IS_REQUIRED": "Se necesita nombre de grupo",
    "GROUP_NAME_MUST_BE_AT_LEAST_TWO_CHARACTERS": "El nombre del grupo debe tener al menos 2 caracteres",
    "GROUP_NUMBER_MAX": "El número BLE no puede ser mayor a  255",
    "GROUP_NUMBER_MIN": "El número BLE no puede ser menor que 1",
    "GROUP_NUMBER_PATTERN": "El número BLE debe ser un entero válido",
    "GROUP_NUMBER_REQUIRED": "Se necesita número BLE"
  },
  "DATES": {
    "CREATE_NEW_SEASON": "Crear nueva estación",
    "DEFAULT": "Defecto",
    "DEFAULT_DATES_AND_TIME": "Días y hora por defecto",
    "NO_TIME_RESTRICTION": "Sin restricción de hora",
    "SEASON": "Estación",
    "SEASONS": "Estaciones"
  },
  "DIALOG": {
    "ARE_YOU_SURE": "¿Está seguro?",
    "CHECKOUT": "¿Está seguro que quiere realizar el check out para este huésped? Esta acción no puede deshacerse.",
    "DELETE": "¿Está seguro que quiere borrar esta entrada? Esta acción no puede deshacerse.",
    "DELETE_ERROR": "Sólo se pueden borrar reservas donde no se haya hecho el check in o ya se haya realizado el check out.",
    "ERROR": "Error",
    "YOUR_DATA_HAVE_NOT_BEEN_SAVED_IF_YOU_LEAVE_NOW_THIS_DATA_WILL_BE_LOST": "Los datos no se han guardado. Si cierra se perderán."
  },
  "EULA": {
    "ABOUT": "Acerca de"
  },
  "GENERAL_INFO": {
    "ADDRESS": "Dirección",
    "HOTEL_ADDRESS_IS_REQUIRED": "Se necesita dirección del hotel",
    "HOTEL_NAME_IS_REQUIRED": "Se necesita nombre del hotel",
    "HOTEL_PARAMS": "Parámetros del hotel",
    "NAME": "Nombre",
    "SERVICE_TIME": "Tiempo de servicio",
    "UPDATE_BEACONS_IS_REQUIRED": "Es necesario actualizar hora de llave",
    "UPDATE_ROOM_BEACONS_TIME": "Actualizar hora de llave"
  },
  "GROUP": {
    "ADD_GROUP": "Añadir grupo",
    "BLE_GROUP": "Grupo BLE",
    "CISA_CATEGORY": "Categoría CISA",
    "CISA_ZONE": "Zona CISA",
    "ERROR": "No se ha podido borrar el grupo. Es posible que esté en uso",
    "IS_DEFAULT": "Defecto",
    "MAX_CHOOSE": "Seleccionar máximo {{max}} grupos",
    "NUMBER": "Número BLE",
    "GROUP_WITH_DATES_WARNING": "El número que está asignando tiene control horario. Seleccione un número mayor que 7 para usar un grupo normal"
  },
  "HEADER": {
    "NEW_BOOKING": "Nueva reserva"
  },
  "IMPORT_CONF": {
    "AN_ERROR_OCCURRED_RESETTING_THE_DATABASE": "Se ha producido un error al borrar la base de datos",
    "CONFIGURATION_IMPORTED_SUCCESSFULLY": "Configuración importada con éxito",
    "DATABASE_CORRECTLY_RESET": "Base de datos borrada correctamente",
    "DOWNLOAD_TEMPLATE_CONFIGURATION_FILE": "Descargar plantilla de fichero de configuración",
    "DOWNLOAD_TEMPLATE_ROOM_TYPES_CONFIGURATION_FILE": "Descargar plantilla de fichero de tipos de habitación",
    "GENERAL_CONFIG_FILE": "Importar fichero de configuración general.",
    "IMPORT_CONF": "Importar configuración",
    "IMPORT_NEW_CONFIGURATION_FILE": "Importar nuevo fichero de configuración",
    "INVALID_CONFIGURATION_FILE": "Fichero de configuración no válido",
    "RESETTING_THE_DATABASE_WILL_REMOVE_ALL_THE_DATA_FROM_THE_SYSTEM_PERMANENTLY": "El borrado de la base de datos eliminará los datos del sistema permanentemente",
    "RESET_COMFORT_DATABASE": "Reset comfort",
    "RESET_DATABASE": "Borrar base de datos",
    "ROOM_TYPES_FILE": "Importar fichero de tipos de habitación.",
    "WARNING_IMPORTING_A_NEW_CONFIGURATION_OR_RESETTING_THE_DATABASE_MAY_DAMAGE_ANY_EXISTING_DATA_PLEASE_USE_WITH_CAUTION": "Atención. Importar un nuevo fichero de configuración o borrar la base de datos puede afectar a los datos del sistema. Usar con precaución."
  },
  "KEY_BEACON_&_MAINTENANCE": {
    "ADVERTISING_POWER": "Potencia de aviso",
    "BEACON_INTERVAL": "Intervalo de llaves",
    "BEACON_INTERVAL_VALUE_CANNOT_BE_GREATER_THAN_10000MS": "El intervalo de llaves no puede ser mayor de 10000ms",
    "BEACON_INTERVAL_VALUE_CANNOT_BE_LESS_THAN_100MS": "El intervalo de llaves no puede ser menor de 100ms",
    "CA_TYPE": "Tipo CA",
    "INTERVAL_UPDATE": "Tiempo de actualización de intervalo",
    "KA_FRAME_NUMBER_CANNOT_BE_GREATER_THAN_65535": "Ka no puede ser mayor de 65535",
    "KA_FRAME_NUMBER_CANNOT_BE_LESS_THAN_0": "Ka no puede ser menor de 0",
    "KA_FRAME_NUMBER_OF_PACKETS": "Ka número de paquetes",
    "KP_FRAME_INTERVAL": "Kp frame interval",
    "KP_FRAME_INTERVAL_VALUE_CANNOT_BE_GREATER_THAN_65535S": "Kp frame interval value cannot be greater than 65535s",
    "KP_FRAME_INTERVAL_VALUE_CANNOT_BE_LESS_THAN_0S": "Kp frame interval value cannot be less than 0s",
    "KP_FRAME_NUMBER_CANNOT_BE_GREATER_THAN_65535": "Kp frame number cannot be greater than 65535",
    "KP_FRAME_NUMBER_CANNOT_BE_LESS_THAN_0": "Kp frame number cannot be less than 0",
    "KP_INTERVAL": "KP interval",
    "KX_FRAME_NUMBER_OF_PACKETS": "Kx fram number of packets",
    "RC_FRAME_NUMBER_OF_PACKETS": "Rc frame number of packets",
    "RSSI_FILTER": "RSSI filter",
    "THE_NUMBER_OF_PACKETS_FOR_THE_KX_FRAME_CANNOT_BE_GREATER_THAN_65535": "The number of packets for the kx frame cannot be greater than 65535",
    "THE_NUMBER_OF_PACKETS_FOR_THE_KX_FRAME_CANNOT_BE_LESS_THAN_0": "The number of packets for the kx frame cannot be less than 0",
    "THE_NUMBER_OF_PACKETS_FOR_THE_RC_FRAME_CANNOT_BE_GREATER_THAN_65535": "The number of packets for the rc frame cannot be greater than 65535",
    "THE_NUMBER_OF_PACKETS_FOR_THE_RC_FRAME_CANNOT_BE_LESS_THAN_0": "The number of packets for the rc frame cannot be less than 0",
    "THE_VALUE_MUST_BE_NUMERIC": "The value must be numeric",
    "TIME_TO_CLOSE_DOOR": "Time to close door",
    "WATCH_DOG_FRAME_INTERVAL": "Watch dog frame interval",
    "WATCH_DOG_FRAME_INTERVAL_VALUE_CANNOT_BE_GREATER_THAN_65535S": "Watch dog frame interval value cannot be greater than 65535s",
    "WATCH_DOG_FRAME_INTERVAL_VALUE_CANNOT_BE_LESS_THAN_0S": "Watch dog frame interval value cannot be less than 0s"
  },
  "LICENSE": {
    "LICENSES": "Licencias",
    "FEATURE": "Característica",
    "QUANTITY": "Cantidad",
    "EXPIRED": "Expirado",
    "VERSION": "Versión",
    "RELOAD": "Recargar",
    "INVALID": "Licencia no válida"
  },
  "LOGIN": {
    "LOGIN": "Acceso",
    "PASSWORD": "Contraseña",
    "PASSWORD_IS_REQUIRED": "Se necesita contraseña",
    "USERNAME": "Nombre de usuario",
    "USERNAME_IS_REQUIRED": "Se necesita nombre de usuario",
    "USERNAME_OR_PASSWORD_IS_INVALID": "Usuario o contraseña no válidos"
  },
  "LOGO": {
    "ERROR": "La imagen es demasiado grande",
    "INPUT": "Seleccionar una imagen",
    "RESULT": "Imagen:",
    "TITLE": "Cargar logo",
    "UPDATE_LOGO": "Cargar un logo",
    "UPLOAD_BUTTON": "Cargar"
  },
  "MONTHS": {
    "APRIL": "Abril",
    "AUGUST": "Agosto",
    "DECEMBER": "Diciembre",
    "FEBRUARY": "Febrero",
    "JANUARY": "Enero",
    "JULY": "Julio",
    "JUNE": "Junio",
    "MARCH": "Marzo",
    "MAY": "Mayo",
    "NOVEMBER": "Noviembre",
    "OCTOBER": "Octubre",
    "SEPTEMBER": "Septiembre"
  },
  "MONTH_PICKER_VALIDATION": {
    "DAY_IS_REQUIRED": "Se necesita día",
    "MONTH_IS_REQUIRED": "Se necesita mes"
  },
  "NOTIFICATIONS": {
    "ACCESS24": "La llave {{beacon}} asignada al usuario {{user}} ha accedido a la habitación o suite {{room}}. La llave no se ha actualizado",
    "BLACKLIST": "La llave {{beacon}} asignada a {{user}} está intentando acceder a la habitación o suite {{room}}",
    "CONTROLLER_NOT_DETECTED": "El controlador de la habitación {{room}} no ha sido detectado",
    "DELETE_ALL": "Borrar toda notificación",
    "GATEWAY_UNREACHABLE": "El gateway {{gateway}} no se puede alcanzar. El estado del sistema puede ser inconsistente. Compruébelo lo antes posible.",
    "HOST_GATEWAY_UNREACHABLE": "El gateway host no se puede alcanzar.",
    "HOURS": "La llave de la habitación {{room}} necesita una actualización de tiempo",
    "INVALID": "Liencia no válida",
    "KEY_REQUEST_MESSAGE": "Una nueva reserva necesita una nueva llave",
    "ROOM_REQUEST": "La habitación {{room}} ha solicitado {{description}}"
  },
  "NOTIFICATIONS_CONF": {
    "ACTIVE": "Activo",
    "EMAIL_FORMAT": "Email debe tener un formato válido.",
    "EMAIL_NOTIFICATIONS": "Notificaciones por Email",
    "EMAIL_SENDER": "Transmisor de Email",
    "EMAIL_SENDER_FORMAT": "El transmisor de Email debe tener un formato válido.",
    "EMAIL_SENDER_REQUIRED": "Se necesita transmisor de Email.",
    "NOTIFICATIONS_CONFIGURATIONS": "Notificaciones",
    "PUSH_NOTIFICATIONS": "Enviar notificaciones",
    "REPEAT_EMAIL": "El email no puede repetirse.",
    "REQUIRED": "El transmisor de email es obligatorio cuando las notificaciones por email están activas."
  },
  "PAGINATOR": {
    "ITEMS_PER_PAGE": "Elementos por página",
    "NEXT_PAGE": "Siguiente página",
    "OF": "de",
    "PREVIOUS_PAGE": "Página anterior"
  },
  "QR_CONFIGURATION": {
    "MESSAGE": "Escanear el código QR con la app de móvil"
  },
  "REPORTS": {
    "CLEAR_ALL": "Borrar todo",
    "DEVICE": "Dispositivo",
    "EVENTS": "Evento(s)",
    "FILTERS_ON": "Filtros activos",
    "GATEWAY": "Gateway",
    "ROOM_AREA_SUITE": "Habitación/Área/Suite",
    "SUBTYPE": "Subtipo",
    "USER": "Uusario"
  },
  "REQUESTS": {
    "REQUEST_TYPE": "Solicitar tipo",
    "REQUEST_TYPE_NAME": "Solicitar nombre de tipo"
  },
  "REQUEST_TYPE": {
    "ERROR": "No se ha podido borrar el tipo de solicitud de habitación. Puede que esté en uso",
    "REQUEST_TYPE_DESCRIPTION_BE_AT_LEAST_TWO_CHARACTERS": "El tipo de solicitud debe tener al menos 2 caracteres",
    "REQUEST_TYPE_DESCRIPTION_CANNOT_EXCEED_70_CHARACTERS": "El tipo de solicitud no debe exceder de 70 caracteres",
    "REQUEST_TYPE_DESCRIPTION_IS_REQUIRED": "Se necesita tipo de solilcitud",
    "ROOM_REQUEST_TYPE": "Tipo de solicitud de habitación"
  },
  "ROLES": {
    "EDIT_ROLE": "Editar rol",
    "NEW_ROLE": "Nuevo rol",
    "ROLES": "Roles",
    "ROLE_DESCRIPTION": "Descripción de rol",
    "ROLE_DESCRIPTION_IS_REQUIRED": "Se necesita descripción de rol",
    "ROLE_DETAILS": "Detalles de rol",
    "ROLE_NAME": "Nombre de rol",
    "ROLE_NAME_IS_REQUIRED": "Se necesita nombre de rol",
    "ROLE_PERMISSIONS": "Permisos de rol"
  },
  "ROLES_LIST": {
    "AREA_MANAGEMENT": "Gestión de área",
    "AREA_MANAGEMENT_DESCRIPTION": "Gestionar derechos de acceso a áreas y grupos",
    "CUSTOM_CONFIGURATION": "Configuración",
    "CUSTOM_CONFIGURATION_DESCRIPTION": "Modificar horas de check-in/check-out, valores de confort, consignas, estaciones, suites, tipos de tareas, solicitudes y parámetros de puesta en marcha",
    "GUEST_MANAGEMENT": "Gestión de huéspedes",
    "GUEST_MANAGEMENT_DESCRIPTION": "Asignar habitaciones y áreas, check-in y check-out de huésped y definición de suites.",
    "KEY_BEACON_COMMISSIONING": "Puesta en marcha de llave",
    "KEY_BEACON_COMMISSIONING_DESCRIPTION": "Configurar llaves por app",
    "NOTIFICATIONS_CONFIGURATION": "Configuración de notificaciones",
    "NOTIFICATIONS_CONFIGURATION_DESCRIPTION": "Configuración de notificaciones",
    "REPORTS": "Informes",
    "REPORTS_DESCRIPTION": "Comprobar informes y exportarlos",
    "ROOM_BEACON_COMMISSIONING": "Puesta en marcha de llave",
    "ROOM_BEACON_COMMISSIONING_DESCRIPTION": "Configurar llaves por app",
    "SERVICE_MANAGEMENT": "Gestión de servicio",
    "SERVICE_MANAGEMENT_DESCRIPTION": "Grupos de servicio y asignación de tareas",
    "SYSTEM_CONFIGURATION": "Configuración de sistema",
    "SYSTEM_CONFIGURATION_DESCRIPTION": "Importar fichero de configuración inicial, interfaz de usuario",
    "TASKS_MANAGEMENT": "Gestión de tareas",
    "TASKS_MANAGEMENT_DESCRIPTION": "Asignar tareas, modificar estado de tareas",
    "USER_MANAGEMENT": "Gestión de usuario",
    "USER_MANAGEMENT_DESCRIPTION": "Gestionar usuarios y roles"
  },
  "ROOMS": {
    "AREA": "AREA",
    "AREA_GROUPS": "Grupos de área",
    "ASSIGN": "Asignar",
    "ASSIGNED_BEACON": "Llave asignada",
    "ASSIGNED_TO": "Asignado a",
    "ASSIGN_ROOM": "Asignar habitación",
    "AVAILABLE": "Disponible",
    "BLACKLISTED_BEACONS": "Llaves en lista negra",
    "BLIND": "Persiana",
    "BLIND_ANGLE": "Ángulo de persiana",
    "BLIND_HEIGHT": "Posición de persiana",
    "BUILDING": "Edificio",
    "CLIMATE": "Aire acondicionado",
    "COMFORT_LIGHT_OFF": "Off",
    "COMFORT_LIGHT_ON": "On",
    "COMFORT_STATUS": "Modo de confort actual",
    "DAYS_TO_CHECKOUT": "Días para checkout",
    "DELTA_ECONOMY": "Economía delta",
    "DELTA_PRE_COMFORT": "Pre confort delta",
    "DO_NOT_DISTURB": "No molestar",
    "FAN_OPERATION": "Modo operación ventilador",
    "FAN_SPEED": "Velocidad ventilador",
    "FLOOR": "Planta",
    "FORCE_PRESENCE": "Forzar presencia",
    "GO_TO_BOOKINGS": "Ir a reservas",
    "GUESTS_IN_ROOM": "Huéspedes en habitación",
    "GUEST_IN_ROOM": "Huésped en habitación",
    "EMPTY_ROOM": "Habitación vacía",
    "LIGHTS": "Luces",
    "LIGHT_STATUS": "Estado de luces",
    "LIST_OF_THE_AREA_GROUPS_THIS_ROOM_BELONGS_TO": "Lista de los grupos de área a los que pertenece esta habitación",
    "LIST_OF_THE_TASKS_REQUESTED_FOR_THIS_ROOM_THAT_HAVE_NOT_BEEN_FULFILLED YET": "Lista de las tareas solicitadas por esta habitación que no se han completado todavía",
    "MAIN_SET_POINT": "Consigna principal",
    "NAME_ASC": "Nombre - ascendente",
    "NAME_DESC": "Nombre - descendente",
    "NEW_TASK": "Nueva tarea",
    "NO_ALARMS": "No hay alarmas activas para esta habitación",
    "NO_GROUPS_HAVE_BEEN_SPECIFIED_FOR_THIS_ROOM": "No se han definido grupos para esta habitación",
    "NO_PENDING_TASKS": "Sin tareas pendientes",
    "OCCUPIED": "Ocupado",
    "OPEN_DOOR": "Abrir puerta",
    "PENDING_TASKS": "Tareas pendientes",
    "REAL_TEMPERATURE": "Temperatura de la habitación",
    "RESERVATIONS": "Reservas",
    "ROOM": "HABITACIÓN",
    "ROOM_DETAILS": "Detalles de habitación",
    "ROOM_STATUS": "Estado de habitación",
    "ROOM_STATUS_NAME": "Nombre de estado de habitación",
    "SCENARIO": "Escenario",
    "LIGHTING_AND_BLINDS": "Iluminación y persianas",
    "SEASON": "Estación",
    "SERVICE_IN_ROOM": "Servicio en la habitación",
    "SORT_BY": "Ordenar por",
    "SUITE": "SUITE",
    "SUITE_ROOMS": "Habitaciones asignadas",
    "TEMPERATURE": "Temperatura",
    "TYPE_ASC": "Tipo - ascendente",
    "TYPE_DESC": "Tipo - descendente",
    "USER_DELTA": "Delta de usuario",
    "VIEW_DETAILS": "Detalles de vista",
    "VISIBLE_SET_POINT": "Consigna visible",
    "VISIBLE_TEMPERATURE": "Consigna activa"
  },
  "ROOM_STATUS": {
    "ROOM_STATUS": "Estado de habitación",
    "ROOM_STATUS_CANNOT_EXCEED_70_CHARACTERS": "El estado de habitación no debe exceder de 70 caracteres",
    "ROOM_STATUS_MUST_BE_AT_LEAST_TWO_CHARACTERS": "El estado de habitación debe tener al menos 2 caracteres",
    "ROOM_STATUS_NAME_IS_REQUIRED": "Se necesita nombre de estado de habitación"
  },
  "SEARCH": {
    "SEARCH_ELLIPSIS": "Búsqueda..."
  },
  "SEASON_PRESET": {
    "CREATE_ERROR": "El rango de fechas pertenece a otra estación",
    "NONE": "Ninguno",
    "SELECT": "Seleccionar una configuración"
  },
  "SECTIONS": {
    "ALARMS": "Alarmas",
    "ASSIGN_TASK": "Asignar tarea",
    "TASKS": "Tareas",
    "BEACONS": "Llaves",
    "BLACKLIST": "Lista negra",
    "COMMON_AREAS": "Áreas comunes",
    "CONF": {
      "AREA_ORGANIZATION": "Organización de áreas",
      "COMFORT_PRESETS": "Configuraciones de confort",
      "COMMISSIONING": "Puesta en marcha",
      "DATES_AND_TIMES": "Fechas y horas",
      "ENCRYPTION": "Encriptación",
      "GENERAL_INFO": "Información general",
      "LICENSES": "Licencias",
      "IMPORT": "Importar",
      "NOTIFICATIONS_CONF": "Notificaciones",
      "QR_CONFIGURATION": "Configuración QR",
      "ROLES": "Roles",
      "ROOM_REQUEST": "Solicitud de habitación",
      "ROOM_STATUS": "Estado de habitación",
      "SECURITY": "Seguridad",
      "STAFF": "Staff",
      "STAFF_ORGANIZATION": "Organización de staff",
      "SUITES": "Suites",
      "UPLOAD_LOGO": "Cargar logo",
      "USER_INTERFACE": "Interfaz de usuario"
    },
    "CONFIGURATION": "Configuración",
    "EULA": "Eula",
    "QR_CONFIGURATION": "Configuración QR"
  },
  "SECURITY": {
    "CONFIGURATION": "Configuración de seguridad",
    "ENCRYPTION": "Encriptación",
    "ENCRYPT_GUEST_DATA_FOR_QR_CODE": "Encriptar datos de huésped para código QR",
    "MAX_LENGTH": "Longitud máxima",
    "MIN_LENGTH": "Longitud mínima",
    "PASSWORD": "Contraseña"
  },
  "SET_POINT": {
    "ADD_SEASON": "Añadir estación",
    "DATE_FROM": "Fecha desde",
    "DATE_TO": "Fecha hasta",
    "EDIT_SEASON": "Editar estación",
    "SET_POINT_CANNOT_EXCEED_70_CHARACTERS": "La consigna no debe exceder de 70 caracteres",
    "SET_POINT_MUST_BE_AT_LEAST_TWO_CHARACTERS": "La consigna debe tener al menos 2 caracteres",
    "SET_POINT_NAME_IS_REQUIRED": "Se requiere nombre de consigna"
  },
  "SHARED": {
    "NO_ITEM_FOUND": "Elemento {{item}} no encontrado."
  },
  "SPACES": {
    "AREA": "Área",
    "ROOM": "Habitación",
    "SUITE": "Suite"
  },
  "STAFF": {
    "ADD_GROUP": "Añadir grupo",
    "ASSIGN_BEACON": "Asignar llave",
    "CLEAR_SELECTION": "Borrar selección",
    "CONFIRM_MEMBER_PASSWORD": "Confirmar contraseña",
    "CREATE_NEW_GROUP": "Crear nuevo grupo",
    "CREATE_STAFF_MEMBER": "Crear miembro de staff",
    "DEFAULT_AREAS": "Áreas por defecto",
    "DELETE_GROUP": "Borrar grupo",
    "EDIT_GROUP": "Editar grupo",
    "EDIT_STAFF_MEMBER": "Editar miembro de staff",
    "GROUPS": "Grupos",
    "HOTEL_ACCESS": "Acceso a hotel",
    "MEMBER_DETAILS": "Detalles de miembro",
    "MEMBER_LAST_NAME": "Apellido de miembro",
    "MEMBER_NAME": "Nombre de miembro",
    "MEMBER_PASSWORD": "Contraseña de miembro",
    "MEMBER_ROLE": "Rol de miembro",
    "MEMBER_USERNAME": "Nombre de usuario de miembro",
    "NO_AREAS": "Sin áreas asignadas.",
    "PASSWORD_AND_CONFIRM_PASSWORD_MUST_BE_THE_SAME": "La contraseña y la confirmación deben coincidir",
    "SELECT_DEFAULT_AREAS": "Seleccionar áreas por defecto",
    "STAFF_MEMBERS": "Miembros de staff",
    "STAFF_MEMBERS_TITLE": "Miembros de staff",
    "STAFF_NAME_CANNOT_EXCEED_70_CHARACTERS": "El nombre del staff no debe exceder de 70 caracteres",
    "STAFF_NAME_IS_REQUIRED": "Se necesita nombre de staff",
    "STAFF_NAME_MUST_BE_AT_LEAST_TWO_CHARACTERS": "El nombre de staff debe tener al menos 2 caracteres",
    "STAFF_PASSWORD_CANNOT_EXCEED_32_CHARACTERS": "El nombre del staff no debe exceder de 32 caracteres.",
    "STAFF_PASSWORD_IS_REQUIRED": "Se necesita contraseña de staff",
    "STAFF_PASSWORD_MUST_BE_AT_LEAST_8_CHARACTERS": "La contraseña de staff debe tener al menos 8 caracteres.",
    "STAFF_PASSWORD_MUST_BE_CONFIRMED": "La contraseña de staff debe confirmarse",
    "STAFF_PASSWORD_SPECIALS_CHARACTERS": "La contraseña de staff debe tener al menos una letra, un número y un caracter especial.",
    "STAFF_SURNAME_CANNOT_EXCEED_70_CHARACTERS": "El apellido de staff no debe exceder de 70 caracteres",
    "STAFF_SURNAME_IS_REQUIRED": "Se necesita apellido de staff",
    "STAFF_SURNAME_MUST_BE_AT_LEAST_TWO_CHARACTERS": "El apellido de staff debe tener al menos 2 caracteres",
    "STAFF_USERNAME_CANNOT_EXCEED_70_CHARACTERS": "El apellido de staff no debe exceder de 70 caracteres",
    "STAFF_USERNAME_IS_REQUIRED": "Se necesita nombre de usuario de staff",
    "STAFF_USERNAME_MUST_BE_AT_LEAST_8_CHARACTERS": "El nombre de usuario de staff debe tener al menos 8 caracteres"
  },
  "SUITES": {
    "CHOOSE_ONE_OR_MORE_ROOM_COMBINATIONS_YOU_WANT_TO_ENABLE_AS_SUITE": "Seleccione la combinación de habitaciones que quiere habilitar como suite",
    "ENABLE_OR_DISABLE_SUITES": "Habilitar o deshabilitar suites",
    "ROOM_IS_OCCUPIED": "Una habitación está ocupada",
    "SAVE_SUITES": "Guardar suites",
    "SUITES": "Suites"
  },
  "TABLE_HEADER": {
    "HIDE_FILTER": "Ocultar filtro",
    "SHOW_FILTER": "Mostrar filtro"
  },
  "TASKS": {
    "ALLOW_FREE_TEXT": "Permitir texto libre",
    "ASSIGNMENT_TASK": "Tarea de asignación",
    "ROOM_SUITE_AREA": "Habitación/Suite/Área",
    "TASK": "Tarea",
    "TASKS": "Tareas",
    "TASK_COMMENT": "Comentario de tarea",
    "TASK_COMMENT_CANNOT_EXCEED_70_CHARACTERS": "El comentario de la tarea no debe exceder de 70 caracteres",
    "TASK_COMMENT_MUST_BE_AT_LEAST_TWO_CHARACTERS": "El comentario de tarea debe tener al menos dos caracteres",
    "TASK_NAME": "Nombre de tarea",
    "TASK_NAME_CANNOT_EXCEED_70_CHARACTERS": "El nombre de tarea no debe exceder de 70 caracteres",
    "TASK_NAME_IS_REQUIRED": "Se necesita nombre de tarea",
    "TASK_NAME_MUST_BE_AT_LEAST_TWO_CHARACTERS": "El nombre de tarea debe tener al menos 2 caracteres",
    "TASK_STATUS": "Estado",
    "TASK_SPACE_IS_REQUIRED": "Se requiere Habitación/Suite/Area",
    "TASK_STATUS_IS_REQUIRED": "Se requiere estado",
    "TASK_TYPE": "Tipo de tarea",
    "USER_GROUP": "Grupo de usuario",
    "USER_GROUPS": "Grupos de usuarios"
  },
  "TASK_TYPES": {
    "ERROR": "Error al borrar tipo de tarea. Comprobar si está asignada a alguna tarea.",
    "TASK_TYPES": "Tipos de tarea",
    "TASK_TYPES_TABLE": "Tipos de tarea(s)"
  },
  "UI_CONFIGURATION": {
    "DRAG_AND_DROP_MENU_SECTIONS_TO_CONFIGURE_THE_ORDER_PRESS_SAVE_TO_KEEP_THE_CHANGES": "Arrastrar secciones de menú para configurar el orden. Pulsar 'Guardar' para mantener los cambios. ",
    "HIDE_APPLICATIONS_HEADER_BAR": "Ocultar barra de cabecera de aplicaciones",
    "INITIAL_PAGE": "Página de inicio",
    "SET_AS_INITIAL_PAGE": "Guardar como página de inicio"
  },
  "WRITE_BEACON": {
    "ACCESS_RIGHTS": "Derechos de acceso",
    "BACK_TO_DETAILS": "Volver a detalles",
    "DESCRIPTION": "Ha completado con éxito el check-in de un nuevo cliente",
    "KEY_READER": "Key reader",
    "NEW_CHECK-IN": "Nuevo check-in",
    "NO_TIME_RESTRICTION": "Sin restricción de tiempo",
    "SCAN_THE_QR_CODE_WITH_THE_MOBILE_APP": "Escanear el código QR con la app de móvil",
    "STAFF": "Ha asignado con éxito la llave a un miembro de staff",
    "SUCCESS": "Éxito",
    "SUMMARY": "Resumen",
    "WRITE_CARD": "Escribir tarjeta",
    "WRITE_SELECTED_BEACON": "Escribir llave seleccionada"
  }
}
